database_tools/__init__.py
database_tools/config.py
database_tools/exceptions.py
database_tools/query_builder.py
database_tools/repository.py
database_tools/server.py
oriona_database_tools-0.4.6.dist-info/METADATA
oriona_database_tools-0.4.6.dist-info/WHEEL
oriona_database_tools-0.4.6.dist-info/entry_points.txt
oriona_database_tools-0.4.6.dist-info/RECORD
