Metadata-Version: 2.4
Name: oriona-database-tools
Version: 0.4.6
Summary: MCP server providing database exploration and query tools for AI assistants
Author-email: Oriona <support@oriona.ai>
License: MIT
Keywords: ai,assistant,database,mcp,sql
Classifier: Development Status :: 4 - Beta
Classifier: Intended Audience :: Developers
Classifier: License :: OSI Approved :: MIT License
Classifier: Programming Language :: Python :: 3
Classifier: Programming Language :: Python :: 3.10
Classifier: Programming Language :: Python :: 3.11
Classifier: Programming Language :: Python :: 3.12
Classifier: Topic :: Database
Classifier: Topic :: Software Development :: Libraries :: Python Modules
Requires-Python: >=3.10
Requires-Dist: aiodns>=3.0.0
Requires-Dist: aiohttp>=3.8.0
Requires-Dist: google-cloud-bigquery>=3.0.0
Requires-Dist: mcp>=1.0.0
Requires-Dist: psycopg2-binary>=2.9.0
Requires-Dist: pydantic-settings>=2.0.0
Requires-Dist: pydantic>=2.0.0
Requires-Dist: pymssql>=2.2.0
Requires-Dist: pymysql>=1.1.0
Requires-Dist: python-dotenv>=1.0.0
Requires-Dist: sqlalchemy-bigquery>=1.6.0
Requires-Dist: sqlalchemy>=2.0.0
Requires-Dist: sqlparse>=0.4.0
Provides-Extra: dev
Requires-Dist: aiosqlite>=0.19.0; extra == 'dev'
Requires-Dist: hypothesis>=6.0.0; extra == 'dev'
Requires-Dist: pytest-asyncio>=0.21.0; extra == 'dev'
Requires-Dist: pytest-benchmark>=4.0.0; extra == 'dev'
Requires-Dist: pytest-cov>=4.0.0; extra == 'dev'
Requires-Dist: pytest-mock>=3.10.0; extra == 'dev'
Requires-Dist: pytest>=7.0.0; extra == 'dev'
